llama_index/storage/docstore/postgres/__init__.py
llama_index/storage/docstore/postgres/base.py
llama_index_storage_docstore_postgres-0.4.1.dist-info/METADATA
llama_index_storage_docstore_postgres-0.4.1.dist-info/WHEEL
llama_index_storage_docstore_postgres-0.4.1.dist-info/licenses/LICENSE
llama_index_storage_docstore_postgres-0.4.1.dist-info/RECORD
