Metadata-Version: 2.4
Name: llama-index-storage-docstore-postgres
Version: 0.4.1
Summary: llama-index docstore postgres integration
Author-email: Your Name <you@example.com>
License-Expression: MIT
License-File: LICENSE
Requires-Python: <4.0,>=3.9
Requires-Dist: llama-index-core<0.15,>=0.13.0
Requires-Dist: llama-index-storage-kvstore-postgres<0.5,>=0.4.0
